LICENSE
README.md
setup.py
OpenCashPeerClient.egg-info/PKG-INFO
OpenCashPeerClient.egg-info/SOURCES.txt
OpenCashPeerClient.egg-info/dependency_links.txt
OpenCashPeerClient.egg-info/entry_points.txt
OpenCashPeerClient.egg-info/not-zip-safe
OpenCashPeerClient.egg-info/top_level.txt
openCashPeerClient/__init__.py
openCashPeerClient/client.py
openCashPeerClient/utils/__init__.py
openCashPeerClient/utils/pow.py