Metadata-Version: 1.0
Name: OpenCashPeerClient
Version: 0.0.0
Summary: OpenCash client that connects to get peers
Home-page: http://github.com/saavedra29/openCashPeerClient
Author: Aristeidis Tomaras
Author-email: arisgold29@gmail.com
License: MIT
Platform: UNKNOWN
